acentoweb.addusergroup-1.0-py3.8-nspkg.pth
acentoweb/.DS_Store
acentoweb/addusergroup/.DS_Store
acentoweb/addusergroup/__init__.py
acentoweb/addusergroup/configure.zcml
acentoweb/addusergroup/event_subscribers.py
acentoweb/addusergroup/interfaces.py
acentoweb/addusergroup/permissions.zcml
acentoweb/addusergroup/setuphandlers.py
acentoweb/addusergroup/testing.py
acentoweb/addusergroup/browser/__init__.py
acentoweb/addusergroup/browser/configure.zcml
acentoweb/addusergroup/browser/overrides/.gitkeep
acentoweb/addusergroup/browser/static/.gitkeep
acentoweb/addusergroup/locales/README.rst
acentoweb/addusergroup/locales/__init__.py
acentoweb/addusergroup/locales/acentoweb.addusergroup.pot
acentoweb/addusergroup/locales/update.py
acentoweb/addusergroup/locales/update.sh
acentoweb/addusergroup/locales/en/LC_MESSAGES/acentoweb.addusergroup.po
acentoweb/addusergroup/profiles/.DS_Store
acentoweb/addusergroup/profiles/default/.DS_Store
acentoweb/addusergroup/profiles/default/browserlayer.xml
acentoweb/addusergroup/profiles/default/catalog.xml
acentoweb/addusergroup/profiles/default/metadata.xml
acentoweb/addusergroup/profiles/default/registry.xml
acentoweb/addusergroup/profiles/default/rolemap.xml
acentoweb/addusergroup/profiles/uninstall/browserlayer.xml
acentoweb/addusergroup/tests/__init__.py
acentoweb/addusergroup/tests/test_robot.py
acentoweb/addusergroup/tests/test_setup.py
acentoweb/addusergroup/tests/robot/test_example.robot
acentoweb.addusergroup-1.0.dist-info/LICENSE
acentoweb.addusergroup-1.0.dist-info/LICENSE.GPL
acentoweb.addusergroup-1.0.dist-info/LICENSE.rst
acentoweb.addusergroup-1.0.dist-info/METADATA
acentoweb.addusergroup-1.0.dist-info/WHEEL
acentoweb.addusergroup-1.0.dist-info/entry_points.txt
acentoweb.addusergroup-1.0.dist-info/namespace_packages.txt
acentoweb.addusergroup-1.0.dist-info/top_level.txt
acentoweb.addusergroup-1.0.dist-info/RECORD
