Metadata-Version: 2.1
Name: acentoweb.addusergroup
Version: 1.0
Summary: Adds new users automatically to groups
Home-page: https://github.com/collective/acentoweb.addusergroup
Author: Espen Moe-Nilssen
Author-email: espen@medialog.no
License: GPL version 2
Project-URL: PyPI, https://pypi.python.org/pypi/acentoweb.addusergroup
Project-URL: Source, https://github.com/collective/acentoweb.addusergroup
Project-URL: Tracker, https://github.com/collective/acentoweb.addusergroup/issues
Keywords: Python Plone CMS
Classifier: Environment :: Web Environment
Classifier: Framework :: Plone
Classifier: Framework :: Plone :: Addon
Classifier: Framework :: Plone :: 5.2
Classifier: Framework :: Plone :: 6.0
Classifier: Programming Language :: Python
Classifier: Programming Language :: Python :: 3.7
Classifier: Programming Language :: Python :: 3.8
Classifier: Programming Language :: Python :: 3.9
Classifier: Operating System :: OS Independent
Classifier: License :: OSI Approved :: GNU General Public License v2 (GPLv2)
Requires-Python: >=3.7
License-File: LICENSE
License-File: LICENSE.GPL
License-File: LICENSE.rst
Requires-Dist: setuptools
Requires-Dist: z3c.jbot
Requires-Dist: plone.api
Requires-Dist: plone.app.dexterity
Requires-Dist: medialog.controlpanel
Provides-Extra: test
Requires-Dist: plone.app.testing ; extra == 'test'
Requires-Dist: plone.testing >=5.0.0 ; extra == 'test'
Requires-Dist: plone.app.contenttypes ; extra == 'test'
Requires-Dist: plone.app.robotframework[debug] ; extra == 'test'
